flask_nameextension/__init__.py
flask_nameextension/core.py
Flask_NameExtension-0.0.1rc0.dist-info/LICENSE
Flask_NameExtension-0.0.1rc0.dist-info/METADATA
Flask_NameExtension-0.0.1rc0.dist-info/WHEEL
Flask_NameExtension-0.0.1rc0.dist-info/top_level.txt
Flask_NameExtension-0.0.1rc0.dist-info/RECORD
