Metadata-Version: 2.1
Name: Flask-NameExtension
Version: 0.0.1rc0
Summary: Flask Extension Template.
Home-page: https://github.com/juniors90/Flask-NameExtension
Author: Ferreira Juan David
Author-email: juandavid9a0@gmail.com
License: The MIT License
Project-URL: Source, https://github.com/juniors90/Flask-NameExtension
Project-URL: Tracker, https://github.com/juniors90/Flask-NameExtension/issues
Project-URL: Donate, https://www.paypal.com/donate?hosted_button_id=LFAQ7E7TJ4HSY
Project-URL: Funding, https://paypal.me/juniors90
Keywords: Template,Flask,Framework
Platform: any
Classifier: Development Status :: 4 - Beta
Classifier: License :: OSI Approved :: MIT License
Classifier: Operating System :: OS Independent
Classifier: Programming Language :: Python
Classifier: Programming Language :: Python :: 3.8
Classifier: Topic :: Internet :: WWW/HTTP :: Dynamic Content
Classifier: Topic :: Software Development :: Libraries :: Python Modules
License-File: LICENSE
Requires-Dist: Flask (>=2.0.1)
